{"code":200,"message":"成功","data":[{"id":17,"createdBy":null,"createdTime":null,"updatedBy":null,"updatedTime":null,"code":"dfsdf6","introduction":"水电费什么的佛山东方，是多么佛是大佛搜都f.smfoisfsodf，没收到佛到付。四大发明斯蒂芬斯福尔无，是佛山佛斯蒂芬孔庙，为佛王飞兮兮，搜到石佛寺，是否及时度U币应不应该与故事老地方没搜到福。没搜烦到死覅的覅斯蒂芬斯尼，四面佛实地要不要比搜方面我IE覅。","name":"路线步骤6","orderIndex":6,"target":"背诵","wayId":7,"wayName":"路线fff1","itemStepLinks":[{"itemId":3,"itemName":null,"itemType":"ARTICLE","stepId":17},{"itemId":4,"itemName":null,"itemType":"ARTICLE","stepId":17}],"appId":1},{"id":16,"createdBy":null,"createdTime":null,"updatedBy":null,"updatedTime":null,"code":"sdfdsmox","introduction":"是多么佛的是覅次次次，面试辅导第四佛。貌似的减肥低分局，手动阀搜地，什么地方iOS地方是，是多么佛是大佛搜都发。","name":"路线步骤5","orderIndex":5,"target":"熟读","wayId":7,"wayName":"路线fff1","itemStepLinks":[{"itemId":14,"itemName":null,"itemType":"BOOK","stepId":16},{"itemId":4,"itemName":null,"itemType":"ARTICLE","stepId":16},{"itemId":8,"itemName":null,"itemType":"ARTICLE","stepId":16},{"itemId":9,"itemName":null,"itemType":"ARTICLE","stepId":16}],"appId":1},{"id":15,"createdBy":null,"createdTime":null,"updatedBy":null,"updatedTime":null,"code":"sdfsfdsaww","introduction":"熟读发多少末次，没收到佛山房小就死了的覅usdo，名称V型欧搜地方搜，，母线槽博苏打绿福搜房网膜偶像 ，没石佛寺杜甫心粗UB月欧美搜辅导费 。貌似佛塑但不，是大佛搜都，了鼎折覆餗的方式写。","name":"路线步骤4","orderIndex":4,"target":"理解","wayId":7,"wayName":"路线fff1","itemStepLinks":[{"itemId":14,"itemName":null,"itemType":"BOOK","stepId":15},{"itemId":4,"itemName":null,"itemType":"ARTICLE","stepId":15},{"itemId":7,"itemName":null,"itemType":"ARTICLE","stepId":15},{"itemId":8,"itemName":null,"itemType":"ARTICLE","stepId":15},{"itemId":3,"itemName":null,"itemType":"ARTICLE","stepId":15}],"appId":1},{"id":14,"createdBy":null,"createdTime":null,"updatedBy":null,"updatedTime":null,"code":"sfmdsf","introduction":"没什么大佛寺地方，什么的佛士大夫利息，低密度覅说服力小偶像欧西。貌似佛挡杀佛is地方水电费，貌似倒是佛山房。没斯蒂芬斯蒂芬iOSU型组成是岁偶的积分。明显从V型四大覅教我们愤怒粗v，水电费磨刀石徐粗粗发。","name":"路线步骤3","orderIndex":3,"target":"理解","wayId":7,"wayName":"路线fff1","itemStepLinks":[{"itemId":4,"itemName":null,"itemType":"ARTICLE","stepId":14}],"appId":1},{"id":13,"createdBy":null,"createdTime":null,"updatedBy":null,"updatedTime":null,"code":"dsmfsdfmsdlf","introduction":"代码佛山的佛似懂非懂，没收到佛山的佛们都是非没搜到，没收到佛双方目的搜房，是多么佛是多么佛士大夫。","name":"路线步骤2","orderIndex":2,"target":"理解","wayId":7,"wayName":"路线fff1","itemStepLinks":[{"itemId":14,"itemName":null,"itemType":"BOOK","stepId":13}],"appId":1},{"id":12,"createdBy":null,"createdTime":null,"updatedBy":null,"updatedTime":null,"code":"dfdsfsfd","introduction":"墨色淡佛挡杀佛莫沃尔夫无法，没收到佛山房没收到覅噢违法w.smdfisdol。。是多么佛门我父母为费分泌性从不不是滴方式分 。没收到吗佛山店覅我if墨为IE覅分分IE 。四大发明山东佛我么法IMICMV易。","name":"路线步骤1","orderIndex":1,"target":"熟练掌握","wayId":7,"wayName":"路线fff1","itemStepLinks":[{"itemId":4,"itemName":null,"itemType":"ARTICLE","stepId":12},{"itemId":7,"itemName":null,"itemType":"ARTICLE","stepId":12},{"itemId":14,"itemName":null,"itemType":"BOOK","stepId":12}],"appId":1}]}